Metadata-Version: 2.1
Name: odoo14-addon-account_banking_mandate_contact
Version: 14.0.1.0.1.dev8
Summary: Assign specific banking mandates in contact level
Home-page: https://github.com/OCA/bank-payment
Author: Tecnativa, Odoo Community Association (OCA)
Author-email: support@odoo-community.org
License: AGPL-3
Classifier: Programming Language :: Python
Classifier: Framework :: Odoo
Classifier: Framework :: Odoo :: 14.0
Classifier: License :: OSI Approved :: GNU Affero General Public License v3
Classifier: Development Status :: 4 - Beta
Requires-Python: >=3.6
Requires-Dist: odoo14-addon-account-banking-mandate
Requires-Dist: odoo<14.1dev,>=14.0a
